<?xml version="1.0" encoding="UTF-8"?>
<quiz>
<question type="stack">
        <name>
            <text>Oppgave 3</text>
        </name>
        <questiontext format="html">
            <text><![CDATA[
<p>
</p>
<p>
    Gitt funksjonen \(f(x)={@exp@}\).
</p>
<p>
    <br/>
</p>
<p>
    \(a)\) Finn \(x\)-verdien til eventuelle nullpunkt til funksjonen \(f\) ved regning. Dersom du mener det ikke eksisterer noen, skriv
    <strong>
        none
    </strong>
    .
</p>
<p>
    \(x=\) [[input:ans1]] [[validation:ans1]]
</p>
<p>
    <br/>
</p>
<p>
    \(b)\) Finn den deriverte av \(f\).
</p>
<p>
    \(f'(x)=\) [[input:ans2]] [[validation:ans2]]
    <br/>
</p>
<p>
    <br/>
</p>
<p>
    \(c)\) Funksjonen \(f\) har ett ekstremalpunkt. Finn punktets koordinater og avgj&#248;r hvilken type det er.
</p>
<p>
    \(x=\)&#160;[[input:ans3]] [[validation:ans3]]&#160; \(y=\)&#160;[[input:ans4]] [[validation:ans4]]
</p>
<p>
    type:&#160;[[input:ans5]] [[validation:ans5]]
</p>
<p>
    <br/>
</p>
<p>
    \(d)\) Finn vendepunktet til \(f\).
</p>
<p>
    \(x=\)&#160;[[input:ans6]] [[validation:ans6]]&#160; \(y=\)&#160;[[input:ans7]] [[validation:ans7]]
    <br/>
</p>
<p>
    <br/>
</p>
<p>
    \(e)\) Finn tangenten i punktet \((1,f(1))\) ved regning.
</p>
<p>
    \(y=\)&#160;[[input:ans8]] [[validation:ans8]]
    <br/>
</p>
<p>
    <br/>
</p>
<p>
    \(f)\) Beregn arealet avgrenset av \(x-\)aksen, linja \(x=1\), linja \(x=2\) og grafen til funksjonen \(f\).
</p>
<p>
    [[input:ans9]] [[validation:ans9]]
    <br/>
</p>
]]></text>
        </questiontext>
        <generalfeedback format="html">
            <text/>
        </generalfeedback>
        <defaultgrade>1.0000000</defaultgrade>
        <penalty>0.1000000</penalty>
        <hidden>0</hidden>
        <idnumber/>
        <stackversion>
            <text>2020070100</text>
        </stackversion>
        <questionvariables>
            <text><![CDATA[exp:(x-1)*e^x;
ta1:solve(exp=0,x);
ta1:ev(x,ta1[1]);
ta2:diff(exp,x);
ta3:0;
ta4:-1;
ta5:[["Toppunkt",false],["Bunnpunkt",true]];
ta5c:"Bunnpunkt";
ta6:-1;
ta7:-2/%e;
ta8:e*x-e;
ta9:int(exp,x,1,2);]]></text>
        </questionvariables>
        <specificfeedback format="html">
            <text><![CDATA[
[[feedback:prt1]]
<br/>
[[feedback:prt2]]
<br/>
[[feedback:prt3]]
<br/>
[[feedback:prt4]]
<br/>
[[feedback:prt5]]
<br/>
[[feedback:prt6]]
<br/>
[[feedback:prt7]]
<br/>
[[feedback:prt8]]
<br/>
[[feedback:prt9]]
<br/>
]]></text>
        </specificfeedback>
        <questionnote>
            <text/>
        </questionnote>
        <questionsimplify>1</questionsimplify>
        <assumepositive>0</assumepositive>
        <assumereal>0</assumereal>
        <prtcorrect format="html">
            <text><![CDATA[
<span style="font-size: 1.5em; color:green;">
    <i class="fa fa-check">
    </i>
</span>
Correct answer, well done.
]]></text>
        </prtcorrect>
        <prtpartiallycorrect format="html">
            <text><![CDATA[
<span style="font-size: 1.5em; color:orange;">
    <i class="fa fa-adjust">
    </i>
</span>
Your answer is partially correct.
]]></text>
        </prtpartiallycorrect>
        <prtincorrect format="html">
            <text><![CDATA[
<span style="font-size: 1.5em; color:red;">
    <i class="fa fa-times">
    </i>
</span>
Incorrect answer.
]]></text>
        </prtincorrect>
        <multiplicationsign>dot</multiplicationsign>
        <sqrtsign>1</sqrtsign>
        <complexno>i</complexno>
        <inversetrig>cos-1</inversetrig>
        <logicsymbol>lang</logicsymbol>
        <matrixparens>[</matrixparens>
        <variantsselectionseed/>
        <input>
            <name>ans1</name>
            <type>algebraic</type>
            <tans>ta1</tans>
            <boxsize>15</boxsize>
            <strictsyntax>1</strictsyntax>
            <insertstars>0</insertstars>
            <syntaxhint/>
            <syntaxattribute>0</syntaxattribute>
            <forbidwords/>
            <allowwords/>
            <forbidfloat>1</forbidfloat>
            <requirelowestterms>0</requirelowestterms>
            <checkanswertype>0</checkanswertype>
            <mustverify>1</mustverify>
            <showvalidation>1</showvalidation>
            <options/>
        </input>
        <input>
            <name>ans2</name>
            <type>algebraic</type>
            <tans>ta2</tans>
            <boxsize>15</boxsize>
            <strictsyntax>1</strictsyntax>
            <insertstars>1</insertstars>
            <syntaxhint/>
            <syntaxattribute>0</syntaxattribute>
            <forbidwords/>
            <allowwords/>
            <forbidfloat>1</forbidfloat>
            <requirelowestterms>0</requirelowestterms>
            <checkanswertype>0</checkanswertype>
            <mustverify>1</mustverify>
            <showvalidation>1</showvalidation>
            <options/>
        </input>
        <input>
            <name>ans3</name>
            <type>algebraic</type>
            <tans>ta3</tans>
            <boxsize>5</boxsize>
            <strictsyntax>1</strictsyntax>
            <insertstars>0</insertstars>
            <syntaxhint/>
            <syntaxattribute>0</syntaxattribute>
            <forbidwords/>
            <allowwords/>
            <forbidfloat>1</forbidfloat>
            <requirelowestterms>0</requirelowestterms>
            <checkanswertype>0</checkanswertype>
            <mustverify>1</mustverify>
            <showvalidation>1</showvalidation>
            <options/>
        </input>
        <input>
            <name>ans4</name>
            <type>algebraic</type>
            <tans>ta4</tans>
            <boxsize>5</boxsize>
            <strictsyntax>1</strictsyntax>
            <insertstars>0</insertstars>
            <syntaxhint/>
            <syntaxattribute>0</syntaxattribute>
            <forbidwords/>
            <allowwords/>
            <forbidfloat>1</forbidfloat>
            <requirelowestterms>0</requirelowestterms>
            <checkanswertype>0</checkanswertype>
            <mustverify>1</mustverify>
            <showvalidation>1</showvalidation>
            <options/>
        </input>
        <input>
            <name>ans5</name>
            <type>dropdown</type>
            <tans>ta5</tans>
            <boxsize>15</boxsize>
            <strictsyntax>1</strictsyntax>
            <insertstars>0</insertstars>
            <syntaxhint/>
            <syntaxattribute>0</syntaxattribute>
            <forbidwords/>
            <allowwords/>
            <forbidfloat>1</forbidfloat>
            <requirelowestterms>0</requirelowestterms>
            <checkanswertype>0</checkanswertype>
            <mustverify>1</mustverify>
            <showvalidation>1</showvalidation>
            <options/>
        </input>
        <input>
            <name>ans6</name>
            <type>algebraic</type>
            <tans>ta6</tans>
            <boxsize>5</boxsize>
            <strictsyntax>1</strictsyntax>
            <insertstars>0</insertstars>
            <syntaxhint/>
            <syntaxattribute>0</syntaxattribute>
            <forbidwords/>
            <allowwords/>
            <forbidfloat>1</forbidfloat>
            <requirelowestterms>0</requirelowestterms>
            <checkanswertype>0</checkanswertype>
            <mustverify>1</mustverify>
            <showvalidation>1</showvalidation>
            <options/>
        </input>
        <input>
            <name>ans7</name>
            <type>algebraic</type>
            <tans>ta7</tans>
            <boxsize>5</boxsize>
            <strictsyntax>1</strictsyntax>
            <insertstars>0</insertstars>
            <syntaxhint/>
            <syntaxattribute>0</syntaxattribute>
            <forbidwords/>
            <allowwords/>
            <forbidfloat>1</forbidfloat>
            <requirelowestterms>0</requirelowestterms>
            <checkanswertype>0</checkanswertype>
            <mustverify>1</mustverify>
            <showvalidation>1</showvalidation>
            <options/>
        </input>
        <input>
            <name>ans8</name>
            <type>algebraic</type>
            <tans>ta8</tans>
            <boxsize>15</boxsize>
            <strictsyntax>1</strictsyntax>
            <insertstars>0</insertstars>
            <syntaxhint/>
            <syntaxattribute>0</syntaxattribute>
            <forbidwords/>
            <allowwords/>
            <forbidfloat>1</forbidfloat>
            <requirelowestterms>0</requirelowestterms>
            <checkanswertype>0</checkanswertype>
            <mustverify>1</mustverify>
            <showvalidation>1</showvalidation>
            <options/>
        </input>
        <input>
            <name>ans9</name>
            <type>algebraic</type>
            <tans>ta9</tans>
            <boxsize>8</boxsize>
            <strictsyntax>1</strictsyntax>
            <insertstars>0</insertstars>
            <syntaxhint/>
            <syntaxattribute>0</syntaxattribute>
            <forbidwords/>
            <allowwords/>
            <forbidfloat>1</forbidfloat>
            <requirelowestterms>0</requirelowestterms>
            <checkanswertype>0</checkanswertype>
            <mustverify>1</mustverify>
            <showvalidation>1</showvalidation>
            <options/>
        </input>
        <prt>
            <name>prt1</name>
            <value>1.0000000</value>
            <autosimplify>1</autosimplify>
            <feedbackstyle>1</feedbackstyle>
            <feedbackvariables>
                <text/>
            </feedbackvariables>
            <node>
                <name>0</name>
                <answertest>AlgEquiv</answertest>
                <sans>ans1</sans>
                <tans>ta1</tans>
                <testoptions/>
                <quiet>0</quiet>
                <truescoremode>=</truescoremode>
                <truescore>1.0000000</truescore>
                <truepenalty/>
                <truenextnode>-1</truenextnode>
                <trueanswernote>prt1-1-T</trueanswernote>
                <truefeedback format="html">
                    <text/>
                </truefeedback>
                <falsescoremode>=</falsescoremode>
                <falsescore>0.0000000</falsescore>
                <falsepenalty/>
                <falsenextnode>-1</falsenextnode>
                <falseanswernote>prt1-1-F</falseanswernote>
                <falsefeedback format="html">
                    <text/>
                </falsefeedback>
            </node>
        </prt>
        <prt>
            <name>prt2</name>
            <value>1.0000000</value>
            <autosimplify>1</autosimplify>
            <feedbackstyle>1</feedbackstyle>
            <feedbackvariables>
                <text/>
            </feedbackvariables>
            <node>
                <name>0</name>
                <answertest>Diff</answertest>
                <sans>ans2</sans>
                <tans>ta2</tans>
                <testoptions>x</testoptions>
                <quiet>0</quiet>
                <truescoremode>=</truescoremode>
                <truescore>1.0000000</truescore>
                <truepenalty/>
                <truenextnode>-1</truenextnode>
                <trueanswernote>prt2-1-T</trueanswernote>
                <truefeedback format="html">
                    <text/>
                </truefeedback>
                <falsescoremode>=</falsescoremode>
                <falsescore>0.0000000</falsescore>
                <falsepenalty/>
                <falsenextnode>-1</falsenextnode>
                <falseanswernote>prt2-1-F</falseanswernote>
                <falsefeedback format="html">
                    <text/>
                </falsefeedback>
            </node>
        </prt>
        <prt>
            <name>prt3</name>
            <value>1.0000000</value>
            <autosimplify>1</autosimplify>
            <feedbackstyle>1</feedbackstyle>
            <feedbackvariables>
                <text/>
            </feedbackvariables>
            <node>
                <name>0</name>
                <answertest>AlgEquiv</answertest>
                <sans>ans3</sans>
                <tans>ta3</tans>
                <testoptions/>
                <quiet>0</quiet>
                <truescoremode>=</truescoremode>
                <truescore>1.0000000</truescore>
                <truepenalty/>
                <truenextnode>-1</truenextnode>
                <trueanswernote>prt3-1-T</trueanswernote>
                <truefeedback format="html">
                    <text/>
                </truefeedback>
                <falsescoremode>=</falsescoremode>
                <falsescore>0.0000000</falsescore>
                <falsepenalty/>
                <falsenextnode>-1</falsenextnode>
                <falseanswernote>prt3-1-F</falseanswernote>
                <falsefeedback format="html">
                    <text/>
                </falsefeedback>
            </node>
        </prt>
        <prt>
            <name>prt4</name>
            <value>1.0000000</value>
            <autosimplify>1</autosimplify>
            <feedbackstyle>1</feedbackstyle>
            <feedbackvariables>
                <text/>
            </feedbackvariables>
            <node>
                <name>0</name>
                <answertest>AlgEquiv</answertest>
                <sans>ans4</sans>
                <tans>ta4</tans>
                <testoptions/>
                <quiet>0</quiet>
                <truescoremode>=</truescoremode>
                <truescore>1.0000000</truescore>
                <truepenalty/>
                <truenextnode>-1</truenextnode>
                <trueanswernote>prt4-1-T</trueanswernote>
                <truefeedback format="html">
                    <text/>
                </truefeedback>
                <falsescoremode>=</falsescoremode>
                <falsescore>0.0000000</falsescore>
                <falsepenalty/>
                <falsenextnode>-1</falsenextnode>
                <falseanswernote>prt4-1-F</falseanswernote>
                <falsefeedback format="html">
                    <text/>
                </falsefeedback>
            </node>
        </prt>
        <prt>
            <name>prt5</name>
            <value>1.0000000</value>
            <autosimplify>1</autosimplify>
            <feedbackstyle>1</feedbackstyle>
            <feedbackvariables>
                <text/>
            </feedbackvariables>
            <node>
                <name>0</name>
                <answertest>String</answertest>
                <sans>ans5</sans>
                <tans>ta5c</tans>
                <testoptions/>
                <quiet>0</quiet>
                <truescoremode>=</truescoremode>
                <truescore>1.0000000</truescore>
                <truepenalty/>
                <truenextnode>-1</truenextnode>
                <trueanswernote>prt5-1-T</trueanswernote>
                <truefeedback format="html">
                    <text/>
                </truefeedback>
                <falsescoremode>=</falsescoremode>
                <falsescore>0.0000000</falsescore>
                <falsepenalty/>
                <falsenextnode>-1</falsenextnode>
                <falseanswernote>prt5-1-F</falseanswernote>
                <falsefeedback format="html">
                    <text/>
                </falsefeedback>
            </node>
        </prt>
        <prt>
            <name>prt6</name>
            <value>1.0000000</value>
            <autosimplify>1</autosimplify>
            <feedbackstyle>1</feedbackstyle>
            <feedbackvariables>
                <text/>
            </feedbackvariables>
            <node>
                <name>0</name>
                <answertest>AlgEquiv</answertest>
                <sans>ans6</sans>
                <tans>ta6</tans>
                <testoptions/>
                <quiet>0</quiet>
                <truescoremode>=</truescoremode>
                <truescore>1.0000000</truescore>
                <truepenalty/>
                <truenextnode>-1</truenextnode>
                <trueanswernote>prt6-1-T</trueanswernote>
                <truefeedback format="html">
                    <text/>
                </truefeedback>
                <falsescoremode>=</falsescoremode>
                <falsescore>0.0000000</falsescore>
                <falsepenalty/>
                <falsenextnode>-1</falsenextnode>
                <falseanswernote>prt6-1-F</falseanswernote>
                <falsefeedback format="html">
                    <text/>
                </falsefeedback>
            </node>
        </prt>
        <prt>
            <name>prt7</name>
            <value>1.0000000</value>
            <autosimplify>1</autosimplify>
            <feedbackstyle>1</feedbackstyle>
            <feedbackvariables>
                <text/>
            </feedbackvariables>
            <node>
                <name>0</name>
                <answertest>AlgEquiv</answertest>
                <sans>ans7</sans>
                <tans>ta7</tans>
                <testoptions/>
                <quiet>0</quiet>
                <truescoremode>=</truescoremode>
                <truescore>1.0000000</truescore>
                <truepenalty/>
                <truenextnode>-1</truenextnode>
                <trueanswernote>prt7-1-T</trueanswernote>
                <truefeedback format="html">
                    <text/>
                </truefeedback>
                <falsescoremode>=</falsescoremode>
                <falsescore>0.0000000</falsescore>
                <falsepenalty/>
                <falsenextnode>-1</falsenextnode>
                <falseanswernote>prt7-1-F</falseanswernote>
                <falsefeedback format="html">
                    <text/>
                </falsefeedback>
            </node>
        </prt>
        <prt>
            <name>prt8</name>
            <value>1.0000000</value>
            <autosimplify>1</autosimplify>
            <feedbackstyle>1</feedbackstyle>
            <feedbackvariables>
                <text/>
            </feedbackvariables>
            <node>
                <name>0</name>
                <answertest>AlgEquiv</answertest>
                <sans>ans8</sans>
                <tans>ta8</tans>
                <testoptions/>
                <quiet>0</quiet>
                <truescoremode>=</truescoremode>
                <truescore>1.0000000</truescore>
                <truepenalty/>
                <truenextnode>-1</truenextnode>
                <trueanswernote>prt8-1-T</trueanswernote>
                <truefeedback format="html">
                    <text/>
                </truefeedback>
                <falsescoremode>=</falsescoremode>
                <falsescore>0.0000000</falsescore>
                <falsepenalty/>
                <falsenextnode>-1</falsenextnode>
                <falseanswernote>prt8-1-F</falseanswernote>
                <falsefeedback format="html">
                    <text/>
                </falsefeedback>
            </node>
        </prt>
        <prt>
            <name>prt9</name>
            <value>1.0000000</value>
            <autosimplify>1</autosimplify>
            <feedbackstyle>1</feedbackstyle>
            <feedbackvariables>
                <text/>
            </feedbackvariables>
            <node>
                <name>0</name>
                <answertest>AlgEquiv</answertest>
                <sans>ans9</sans>
                <tans>ta9</tans>
                <testoptions/>
                <quiet>0</quiet>
                <truescoremode>=</truescoremode>
                <truescore>1.0000000</truescore>
                <truepenalty/>
                <truenextnode>-1</truenextnode>
                <trueanswernote>prt9-1-T</trueanswernote>
                <truefeedback format="html">
                    <text/>
                </truefeedback>
                <falsescoremode>=</falsescoremode>
                <falsescore>0.0000000</falsescore>
                <falsepenalty/>
                <falsenextnode>-1</falsenextnode>
                <falseanswernote>prt9-1-F</falseanswernote>
                <falsefeedback format="html">
                    <text/>
                </falsefeedback>
            </node>
        </prt>
    </question>
    

</quiz>